{
    "backend": "flask",
    "db_name": "",
    "db_pass": "",
    "db_type": "mysql",
    "db_user": "",
    "dbms": "1",
    "description": "generated product",
    "design": "soft-ui-dashboard",
    "docker": "0",
    "err_code": 0,
    "frontend": "",
    "heroku": "1",
    "pattern": "mvc",
    "pro": "0",
    "task_id": "97e52fa4-9bf2-4381-988c-8e3da8be8fd6",
    "task_info": "Upload Sources [0%] - 332 files",
    "task_output": "97e52fa4-9bf2-4381-988c-8e3da8be8fd6.zip",
    "task_result": "SUCCESS",
    "task_state": "RUNNING",
    "task_ts_end": "2023-10-18-03-08-06",
    "task_ts_start": "2023-10-18-03-08-03"
}